sleek_ytdner/__init__.py
sleek_ytdner/app.py
sleek_ytdner/static/favicon.png
sleek_ytdner/static/css/style.css
sleek_ytdner/static/images/logo.png
sleek_ytdner/static/js/script.js
sleek_ytdner/templates/index.html
sleek_ytdner/templates/intro.html
sleek_ytdner-1.2.dist-info/licenses/LICENSE
sleek_ytdner-1.2.dist-info/licenses/LICENSE_ko.md
sleek_ytdner-1.2.dist-info/METADATA
sleek_ytdner-1.2.dist-info/WHEEL
sleek_ytdner-1.2.dist-info/entry_points.txt
sleek_ytdner-1.2.dist-info/top_level.txt
sleek_ytdner-1.2.dist-info/RECORD
