Metadata-Version: 2.4
Name: sleek_ytdner
Version: 1.2
Summary: A sleek, theme-aware Youtube Downloader using Flask and yt-dlp
Author-email: "Rheehose (Rhee Creative)" <rheehose@rheehose.com>
License: MIT
Classifier: Programming Language :: Python :: 3
Classifier: Framework :: Flask
Classifier: License :: OSI Approved :: MIT License
Classifier: Operating System :: OS Independent
Requires-Python: >=3.8
License-File: LICENSE
License-File: LICENSE_ko.md
Requires-Dist: Flask
Requires-Dist: yt-dlp
Dynamic: license-file
